[
  {
    "id": 7,
    "type": "video",
    "title": "The Hunt and the heart",
    "description": "The silent battle of the cheetah",
    "url": "https://www.instagram.com/reel/DLxxI_SC4tJ/?igsh=MTZwYTBsMm1sMDQ4OQ==",
    "width": "400",
    "height": "711"
  },
  {
    "id": 2,
    "type": "image",
    "title": "White Rhino",
    "description": "Most endangered species of Rhino",
    "url": "/static/uploads/whiteRhino.jpg",
    "width": "400",
    "height": "400"
  },
  {
    "id": 3,
    "type": "image",
    "title": "baby cheetah",
    "description": "",
    "url": "/static/uploads/images_10_9.jpeg",
    "width": "300",
    "height": "400"
  },
  {
    "id": 4,
    "type": "image",
    "title": "parent cheetah",
    "description": "the fastest land mammal",
    "url": "/static/uploads/images_10_8.jpeg",
    "width": "450",
    "height": "300"
  },
  {
    "id": 5,
    "type": "image",
    "title": "the hippopotamus",
    "description": "pound for pound one of the heaviest land mammals",
    "url": "/static/uploads/Flusspferd_2024_09_27_002_SLE.jpg",
    "width": "500",
    "height": "300"
  },
  {
    "id": 6,
    "type": "image",
    "title": "baby hippo",
    "description": "harmless for now",
    "url": "/static/uploads/images_10_5.jpeg",
    "width": "500",
    "height": "300"
  },
  {
    "id": 7,
    "type": "image",
    "title": "The lion Brothers",
    "description": "the most dangerous duo you can find",
    "url": "/static/uploads/images_10_10.jpeg",
    "width": "400",
    "height": "300"
  },
  {
    "id": 8,
    "type": "image",
    "title": "The lion cub",
    "description": "future king of the jungle",
    "url": "/static/uploads/images_10_15.jpeg",
    "width": "400",
    "height": "300"
  },
  {
    "id": 9,
    "type": "image",
    "title": "callobus monkey",
    "description": "A distinct species of monkey",
    "url": "/static/uploads/images_10_13.jpeg",
    "width": "300",
    "height": "300"
  },
  {
    "id": 10,
    "type": "image",
    "title": "giraffe center",
    "description": "Where you go just to see the giraffes",
    "url": "/static/uploads/images_10_7.jpeg",
    "width": "400",
    "height": "300"
  },
  {
    "id": 11,
    "type": "image",
    "title": "The zebra",
    "description": "Majestic and its own way",
    "url": "/static/uploads/images_10_16.jpeg",
    "width": "400",
    "height": "300"
  },
  {
    "id": 12,
    "type": "image",
    "title": "The African Elephant ",
    "description": "Largest living land mammal",
    "url": "/static/uploads/images_10_14.jpeg",
    "width": "400",
    "height": "300"
  }
]